sp_piracicaba/__init__.py
sp_piracicaba/lyr.py
sp_piracicaba/data/output/geo/divisa_abairramento.7z
sp_piracicaba/data/output/geo/divisa_municipal.7z
sp_piracicaba/data/output/geo/divisa_perimetro.7z
sp_piracicaba/data/output/geo/divisa_urbanorural.7z
sp_piracicaba/data/output/geo/macrozonas.7z
sp_piracicaba-0.0.18.dist-info/LICENSE
sp_piracicaba-0.0.18.dist-info/METADATA
sp_piracicaba-0.0.18.dist-info/WHEEL
sp_piracicaba-0.0.18.dist-info/top_level.txt
sp_piracicaba-0.0.18.dist-info/RECORD
